pydrs/__init__.py
pydrs/base.py
pydrs/pydrs.py
pydrs/utils.py
pydrs/validation.py
pydrs/bsmp/__init__.py
pydrs/bsmp/command.py
pydrs/bsmp/constants.py
pydrs/bsmp/exceptions.py
pydrs/bsmp/interface.py
pydrs/bsmp/pwrsupply.py
pydrs/bsmp/entities/__init__.py
pydrs/bsmp/entities/parameters.py
pydrs/bsmp/entities/ps.py
pydrs/consts/__init__.py
pydrs/consts/common.py
pydrs/consts/fac.py
pydrs/consts/fap.py
pydrs/consts/fbp.py
pydrs/consts/resonant.py
pydrs-2.3.3.dist-info/licenses/LICENSE
pydrs-2.3.3.dist-info/METADATA
pydrs-2.3.3.dist-info/WHEEL
pydrs-2.3.3.dist-info/top_level.txt
pydrs-2.3.3.dist-info/RECORD
