Metadata-Version: 2.4
Name: pydrs
Version: 2.3.3
License: MIT License
Classifier: Intended Audience :: Science/Research
Classifier: Programming Language :: Python :: 3
Classifier: Topic :: Scientific/Engineering
Classifier: Operating System :: OS Independent
Requires-Python: >=3.12.10
License-File: LICENSE
Provides-Extra: dev
Requires-Dist: bandit==1.8.6; extra == "dev"
Requires-Dist: black==25.1.0; extra == "dev"
Requires-Dist: flake8==7.3.0; extra == "dev"
Requires-Dist: flake8-bandit==4.1.1; extra == "dev"
Requires-Dist: flake8-bugbear==24.12.12; extra == "dev"
Requires-Dist: flake8-implicit-str-concat==0.5.0; extra == "dev"
Requires-Dist: mypy==1.18.1; extra == "dev"
Requires-Dist: mypy-extensions==1.1.0; extra == "dev"
Requires-Dist: pyflakes==3.4.0; extra == "dev"
Requires-Dist: types-setuptools; extra == "dev"
Requires-Dist: pytest==8.3.5; extra == "dev"
Dynamic: license-file
